herobrain_sdk/__init__.py
herobrain_sdk/_version.py
herobrain_sdk/basesdk.py
herobrain_sdk/httpclient.py
herobrain_sdk/py.typed
herobrain_sdk/sdk.py
herobrain_sdk/sdkconfiguration.py
herobrain_sdk/_hooks/__init__.py
herobrain_sdk/_hooks/registration.py
herobrain_sdk/_hooks/sdkhooks.py
herobrain_sdk/_hooks/types.py
herobrain_sdk/models/__init__.py
herobrain_sdk/models/components/__init__.py
herobrain_sdk/models/components/anomaly.py
herobrain_sdk/models/components/decaystatus.py
herobrain_sdk/models/components/memory.py
herobrain_sdk/models/components/pattern.py
herobrain_sdk/models/components/security.py
herobrain_sdk/models/components/tierstats.py
herobrain_sdk/models/errors/__init__.py
herobrain_sdk/models/errors/herobraindefaulterror.py
herobrain_sdk/models/errors/herobrainerror.py
herobrain_sdk/models/errors/no_response_error.py
herobrain_sdk/models/errors/responsevalidationerror.py
herobrain_sdk/models/operations/__init__.py
herobrain_sdk/models/operations/get_api_v1_intelligence_tiering_stats.py
herobrain_sdk/models/operations/get_api_v1_memories.py
herobrain_sdk/models/operations/get_api_v1_oauth_consent.py
herobrain_sdk/models/operations/get_api_v1_oauth_scopes.py
herobrain_sdk/models/operations/post_api_v1_intelligence_anomalies.py
herobrain_sdk/models/operations/post_api_v1_intelligence_decay_status.py
herobrain_sdk/models/operations/post_api_v1_intelligence_insights.py
herobrain_sdk/models/operations/post_api_v1_intelligence_run_decay.py
herobrain_sdk/models/operations/post_api_v1_intelligence_run_tiering.py
herobrain_sdk/models/operations/post_api_v1_oauth_consent.py
herobrain_sdk/models/operations/post_api_v1_oauth_revoke.py
herobrain_sdk/models/operations/post_graphql.py
herobrain_sdk/types/__init__.py
herobrain_sdk/types/basemodel.py
herobrain_sdk/utils/__init__.py
herobrain_sdk/utils/annotations.py
herobrain_sdk/utils/datetimes.py
herobrain_sdk/utils/enums.py
herobrain_sdk/utils/eventstreaming.py
herobrain_sdk/utils/forms.py
herobrain_sdk-1.0.0.dist-info/METADATA
herobrain_sdk-1.0.0.dist-info/WHEEL
herobrain_sdk-1.0.0.dist-info/top_level.txt
herobrain_sdk-1.0.0.dist-info/RECORD
