Metadata-Version: 2.4
Name: herobrain-sdk
Version: 1.0.0
Summary: Python SDK for HeroBrain Memory OS - cognitive memory system with intelligence layer
Author: Speakeasy
Requires-Python: >=3.9.2
Requires-Dist: httpcore>=1.0.9
Requires-Dist: httpx>=0.28.1
Requires-Dist: pydantic>=2.11.2
